MovingLineAGIP-0.0.2.dist-info/METADATA
MovingLineAGIP-0.0.2.dist-info/RECORD
MovingLineAGIP-0.0.2.dist-info/WHEEL
MovingLineAGIP-0.0.2.dist-info/top_level.txt
slam_recognition/__init__.py
slam_recognition/end_tensor.py
slam_recognition/vision_filter.py
slam_recognition/center_surround_tensor/__init__.py
slam_recognition/center_surround_tensor/center_surround_tensor.py
slam_recognition/center_surround_tensor/rgby.py
slam_recognition/center_surround_tensor/rgc.py
slam_recognition/edge_tensor/__init__.py
slam_recognition/edge_tensor/edge_tensor.py
slam_recognition/edge_tensor/stripe_tensor.py
slam_recognition/regulator_tensor/__init__.py
slam_recognition/regulator_tensor/gaussian_regulator_tensor.py
slam_recognition/util/__init__.py
slam_recognition/util/attractor/__init__.py
slam_recognition/util/attractor/euclidian_attractor_function.py
slam_recognition/util/attractor/linear_attractor_function.py
slam_recognition/util/attractor/log_attractor_function.py
slam_recognition/util/attractor/piecewise_attractor_function.py
slam_recognition/util/normalize/__init__.py
slam_recognition/util/normalize/normalize_center_surround.py
slam_recognition/util/orientation/__init__.py
slam_recognition/util/orientation/simplex_coordinates.py
slam_recognition/zoom_tensor/__init__.py
slam_recognition/zoom_tensor/from_image.py
slam_recognition/zoom_tensor/to_image_list.py
tests/__init__.py
tests/test_center_surround_tensors.py
tests/test_normalize_center_surround.py
tests/test_simplex_coordinates.py
